billit/__init__.py
billit/client.py
billit/models/__init__.py
billit/models/account.py
billit/models/party.py
billit/models/product.py
billit/tools/__init__.py
billit/tools/account.py
billit/tools/accountant.py
billit/tools/ai_composite.py
billit/tools/document.py
billit/tools/financial_transaction.py
billit/tools/gl_account.py
billit/tools/misc.py
billit/tools/order.py
billit/tools/party.py
billit/tools/peppol.py
billit/tools/product.py
billit/tools/reports.py
billit/tools/to_process.py
billit/tools/webhook.py
billit_mcp/__init__.py
billit_mcp/__main__.py
billit_mcp/server.py
billit_mcp-0.2.20.dist-info/LICENSE
billit_mcp-0.2.20.dist-info/METADATA
billit_mcp-0.2.20.dist-info/WHEEL
billit_mcp-0.2.20.dist-info/entry_points.txt
billit_mcp-0.2.20.dist-info/RECORD
