Metadata-Version: 2.3
Name: billit-mcp
Version: 0.2.20
Summary: Model Context Protocol server for Billit API integration, enabling AI assistants to manage invoices and financial transactions
License: MIT
Keywords: mcp,model-context-protocol,billit,invoice,api,ai,cursor
Author: Markov Kernel
Author-email: support@markov-kernel.com
Requires-Python: >=3.12,<4.0
Classifier: Development Status :: 4 - Beta
Classifier: Intended Audience :: Developers
Classifier: License :: OSI Approved :: MIT License
Classifier: Programming Language :: Python :: 3
Classifier: Programming Language :: Python :: 3.12
Classifier: Programming Language :: Python :: 3.13
Classifier: Topic :: Office/Business :: Financial
Classifier: Topic :: Software Development :: Libraries :: Python Modules
Requires-Dist: fastapi (>=0.115.12,<0.116.0)
Requires-Dist: httpx (>=0.28.1,<0.29.0)
Requires-Dist: mcp (>=1.0.0,<2.0.0)
Requires-Dist: pydantic (>=2.11.5,<3.0.0)
Requires-Dist: python-dotenv (>=1.1.0,<2.0.0)
Requires-Dist: python-multipart (>=0.0.7,<0.0.8)
Requires-Dist: uvicorn[standard] (>=0.34.3,<0.35.0)
Project-URL: Documentation, https://github.com/markov-kernel/Billit-mcp#readme
Project-URL: Homepage, https://github.com/markov-kernel/Billit-mcp
Project-URL: Repository, https://github.com/markov-kernel/Billit-mcp
